{
  "/" : {
    "schema" : {
      "login": "String"
    }
  },
    "/multipart": {
        "schema": {}
    },

    "/logout": {
        "schema": {}
    },
    "/signupAccount": {
        "schema": {}
    },
  "/uploadImage": {
    "schema": {}
  },
  "/index" : {
    "schema" : {
      "login" : "String"
    }
  },
  "/login" : {
    "schema" : {
      "login" : "String"
    }
  },
  "/user": {
    "schema": {
    "_id": "String",
      "_id": {
      "type": "String",
        "required": true,
        "unique": true
    },
    "login"        : "String",
    "password"     : "String"
    }
  },
  "/users": {
    "schema": {
    "_id": "String",
      "_id": {
      "type": "String",
        "required": true,
        "unique": true
    },
    "login"        : "String",
    "password"     : "String"
    }
  },
  "/formadduser" : {
    "schema": {}
  },
  "/adduser" : {
    "schema" : {
      "login" : "String",
      "password" : "String"
    }
  }

}